{"name":"NV DDS","tagline":"DDS image loader for OpenGL2/ OpenGL ES2","body":"## Overview\r\nthis project tracks updates/ bugfixes for the DDS loader from the nvidia SDK and ports it to OpenGL2+ and OpenGL ES2\r\n\r\n### changes\r\n* refactor code for faster execution/ smaller footprint\r\n* gcc 64bit compability\r\n* compability with OpenGL ES2\r\n* correctly handle RGBA, BGRA, RGB, BGR formats (some require ES2 extensions)\r\n* add interface to load files from memory\r\n","google":"","note":"Don't delete this file! It's used internally to help with page regeneration."}